{
	"AndroidIAPList": "com.roblox.client.robux40,com.roblox.robloxmobile.premium80robux,com.roblox.robloxmobile.premium160robux,com.roblox.robloxmobile.premium240robux,com.roblox.robloxmobile.premium320robux,com.roblox.robloxmobile.premium400robux,com.roblox.robloxmobile.premium800robux,com.roblox.robloxmobile.premium1700robux,com.roblox.robloxmobile.premium4500robux,com.roblox.robloxmobile.premium10000robux,com.roblox.client.robux22500,com.roblox.robloxmobile.premium88subscribed,com.roblox.robloxmobile.premium175subscribed,com.roblox.robloxmobile.premium265subscribed,com.roblox.robloxmobile.premium350subscribed,com.roblox.robloxmobile.premium440subscribed2,com.roblox.robloxmobile.premium880subscribed,com.roblox.robloxmobile.premium1870subscribed,com.roblox.robloxmobile.premium4950subscribed,com.roblox.robloxmobile.premium11000subscribed,com.roblox.client.robux25000,com.roblox.client.robux22500,com.roblox.robloxmobile.premium270robux,com.roblox.robloxmobile.premium450robux,com.roblox.robloxmobile.premium550robux,com.roblox.robloxmobile.premium700robux,com.roblox.robloxmobile.premium900robux,com.roblox.robloxmobile.premium1150robux,com.roblox.robloxmobile.premium1550robux,com.roblox.robloxmobile.premium1850robux,com.roblox.robloxmobile.premium2050robux,com.roblox.robloxmobile.premium4250robux,com.roblox.robloxmobile.premium4750robux,com.roblox.robloxmobile.premium5000robux,com.roblox.robloxmobile.premium9500robux,com.roblox.robloxmobile.premium10200robux,com.roblox.robloxmobile.premium9600robux,com.roblox.robloxmobile.premium20500robux,com.roblox.robloxmobile.premium20000robux,com.roblox.robloxmobile.premium21500robux,com.roblox.robloxmobile.premium310subscribed,com.roblox.robloxmobile.premium490subscribed,com.roblox.robloxmobile.premium590subscribed,com.roblox.robloxmobile.premium780subscribed,com.roblox.robloxmobile.premium980subscribed,com.roblox.robloxmobile.premium1230subscribed,com.roblox.robloxmobile.premium1720subscribed,com.roblox.robloxmobile.premium2020subscribed,com.roblox.robloxmobile.premium2220subscribed,com.roblox.robloxmobile.premium4700subscribed,com.roblox.robloxmobile.premium5200subscribed,com.roblox.robloxmobile.premium5450subscribed,com.roblox.robloxmobile.premium10500subscribed,com.roblox.robloxmobile.premium11200subscribed,com.roblox.robloxmobile.premium10600subscribed,com.roblox.robloxmobile.premium23000subscribed,com.roblox.robloxmobile.premium22500subscribed,com.roblox.robloxmobile.premium24000subscribed,com.roblox.robloxmobile.premium10000robuxplusitem,com.roblox.robloxmobile.premium11000robuxplusitemsubscribed,com.roblox.robloxmobile.premium22500robuxplusitem,com.roblox.robloxmobile.premium25000robuxplusitemsubscribed",
	"AndroidInitializeAndroidUpdateAdapter": true,
	"AndroidSendCurrentOrientationAfterSoftwareInitiatedRotation3": false,
	"CatalogPromoAssetId": -1,
	"CrashpadUploadToBacktraceAndroidPlayerToken": "3fd27180e359d21ab86e48526adecaf75bfb062c138eb23e847ef1ed906f9aaf",
	"CrashpadUploadToBacktraceAndroidPlayerToken_PlaceFilter": "30a794c06f5d61e51cf4b0b8103ef2cd7039c6b46bafce0cfba33518d5409010;6036870533",
	"CrashpadUploadToBacktraceUrl": "https://upload.crashes.rbxinfra.com/post",
	"DefaultTapFilterLevel": 0,
	"DeprecationNoticeDeadline": "2021-06-16",
	"DFFlagAlternateMemoryPrioritizationThresholdSubset": false,
	"DFFlagCLI52218a": true,
	"DFFlagCLI52218ad": true,
	"DFFlagCLI52218ag": true,
	"DFFlagCLI52218ai": true,
	"DFFlagCLI52218c": true,
	"DFFlagCLI52218d": true,
	"DFFlagCLI52218p": true,
	"DFFlagCLI52218q": true,
	"DFFlagCLI52218r": true,
	"DFFlagCLI52218s": true,
	"DFFlagCLI52218t": true,
	"DFFlagCLI52218u": true,
	"DFFlagCLI52218v": true,
	"DFFlagCLI52218w": true,
	"DFFlagCLI52218x": true,
	"DFFlagCLI59083": true,
	"DFFlagCLI61776": true,
	"DFFlagCLI61776b": true,
	"DFFlagDebugSendTDigestDebugInfo": false,
	"DFFlagDeferInferredCrashEvaluation": false,
	"DFFlagDeprecationMessageRefinements": true,
	"DFFlagEnableAdSeenStatsReporting": true,
	"DFFlagFlagRolloutTestDynamicBool1_Rollout": "True;60;2024-03-19T23:14:40",
	"DFFlagHttpCacheReportSlowWrites": true,
	"DFFlagInferredCrashDebugFields": true,
	"DFFlagInferredCrashReportDelayedReport": true,
	"DFFlagPlayerConfigurerRunLMSTest": true,
	"DFFlagPredictedOOM": true,
	"DFFlagSessionTelemetryUnify": true,
	"DFFlagStoreUniqueIdInferredCrashSystem": true,
	"DFIntAlternateMemoryPressureTriggerCriticalMB": 150,
	"DFIntAlternateMemoryPressureTriggerLowMB": 250,
	"DFIntAlternateMemoryPressureTriggerMB": 350,
	"DFIntAlternateMemoryPrioritizationThresholdSubsetPercent": 20,
	"DFIntCLI52218aa": 1,
	"DFIntCLI52218ab": 1,
	"DFIntCLI52218ac": 1,
	"DFIntCLI52218ae": 10000,
	"DFIntCLI52218b": 1200,
	"DFIntCLI52218e": 100,
	"DFIntCLI52218f": 200000,
	"DFIntCLI52218g": 1,
	"DFIntCLI52218h": 1,
	"DFIntCLI52218i": 1,
	"DFIntCLI52218j": 1,
	"DFIntCLI52218k": 1,
	"DFIntCLI52218l": 1,
	"DFIntCLI52218m": 10000,
	"DFIntCLI52218n": 4000,
	"DFIntCLI52218o": 1,
	"DFIntCLI52218y": 1,
	"DFIntCLI52218z": 1,
	"DFIntCLI55166": 10000,
	"DFIntCLI61776a": 10000,
	"DFIntCrashpadUploadToBacktracePercentage": 5,
	"DFIntCrashUploadAttachmentKiloByteLimit": 100,
	"DFIntCriticalThermalStatusThreshold": 4,
	"DFIntHttpCacheReportSlowWritesHundredthPercentageSent": 1000,
	"DFIntHttpCacheReportSlowWritesMinDuration": 10000,
	"DFIntImmersiveAdUnloadEventThrottleHundredthsPercent": 10000,
	"DFIntImmersiveAdVideoProgressEventThrottleHundredthsPercent": 10000,
	"DFIntInterpolationDtLimitForLod_PlaceFilter": "12;4924922222",
	"DFIntIosDeprecationDate": "1714374000000",
	"DFIntIosDeprecationPhase": 2,
	"DFIntMinimumNumberMechanismsForMT": 20,
	"DFIntParallelBroadPhaseNewBatchCount": 8,
	"DFStringCLI52218ah": "632312b51afcb4654dbd03594f849f55ca310379c5c66dfe765ea60a086effc6;ba1c4fb89fa4931a5f213b858256fb3f4cd0bdfe5999f8d958169d462942ef00;617036cc9a815d07501cc349eb2d40d132b2eb6961564a969157b1659336ff22;4c27ea5c6131fc887a2c7892fc2552c10aef29ef4debe327337b87ad8841ec4b",
	"DFStringIosDeprecationBodyPhase2LocalizationKey": "IosDeprecationBodyPhase2Fallback",
	"DFStringMemoryBufferForHarmonyData": "{\\\"memCurve\\\":[{\\\"maxsize\\\":1024,\\\"reserve\\\":0.15}]}",
	"DisableLoadingOfRobuxUrlForTencentBuild": false,
	"EnableAndroidAutofillPhoneNumber": true,
	"EnableAndroidAutofillSMSOTP": true,
	"EnableAndroidCredentialsProtocol": true,
	"EnableAndroidRealtimeProtocol": true,
	"EnableAndroidRealtimeProtocolRollout": 0,
	"EnableAppsFlyerFacebookTracking": false,
	"EnableCallNotificationHandler4": true,
	"EnableDOMStorageForAngularWebviewCapabilitiy": true,
	"EnableEnhancedShareAnalytics": true,
	"EnableGameOrientationWithDelayInMs": 0,
	"EnableIrisGameJoinAndroid2": true,
	"EnableIrisUpdatedCallingNotificationCompat": false,
	"EnableMarshallerAsync": false,
	"EnablePushNotificationRegistrationPostLoginFix": true,
	"EnablePushNotificationSessionUtilsAndroid": true,
	"EnablePushNotificationsPromptAndroid13": true,
	"EnableRequestPermissionsOnAppReady": true,
	"EnableSdk33PostNotifications": true,
	"EnableSendrChatNotificationReply": true,
	"EnableSendrThumbnail": true,
	"EnableSessionCheckThroughUserAuthenticatedEndpoint": true,
	"EventStreamBatchSize": 10,
	"FFlagAddExperienceLaunchFieldsToV2Stat": true,
	"FFlagAndroidEnableQoS": true,
	"FFlagAndroidPhoneAutofillShouldApplySanitizationRelease1": true,
	"FFlagAXItemCardRedesignIXPEnabled2": true,
	"FFlagAXTileSizeIXPEnabled": true,
	"FFlagDisableAccountSelectionListScrollingRelease2": true,
	"FFlagEditProfileFixLogging": true,
	"FFlagEnableAccountSwitchFeature": true,
	"FFlagEnableAndroidAutofillPhoneVerificationRelease1": true,
	"FFlagEnableCancelInputEvent": true,
	"FFlagEnableContactInvitesForNonPhoneVerifiedForAll_v2": true,
	"FFlagEnableDeeplinkLoggingPolicy": true,
	"FFlagEnableDidSwitchAccount": true,
	"FFlagEnableHomePageUpsellCardRelease6": true,
	"FFlagEnableHomePageUpsellCardRelease7": true,
	"FFlagEnableInternationalPhoneNumberAutofillRelease1": true,
	"FFlagEnableLoggingInterceptor": true,
	"FFlagEnableLuaAccountSwitchRelease2": true,
	"FFlagEnableLuaPhoneVerificationExperimentRelease1": true,
	"FFlagEnableNavbarLabelExperiment": false,
	"FFlagEnableNavigationPerformanceIntervals2": true,
	"FFlagEnablePrefetchTimeout": true,
	"FFlagEnableRandomRobloxChannelSelection": true,
	"FFlagEnableSeamlessForceOTAUpdate2": true,
	"FFlagEnableSetAndroidUpdateAdapter": true,
	"FFlagEnableSignupBirthdayExperimentsRelease2": true,
	"FFlagEnableTouchHandlingFix": false,
	"FFlagEnableViewabilityTracking3": true,
	"FFlagExperienceDetailsShortUrlEnabledForAll_v1": true,
	"FFlagFixTextMismatchAndOverlap": true,
	"FFlagFlagRolloutTestStaticBool1_Rollout": "True;60;2024-03-19T23:15:43",
	"FFlagFriendInvitesEnabledForSoothsayers_v1": true,
	"FFlagFriendsCarouselEnabled_v2": true,
	"FFlagGraphicsGLEnableHQShadersExclusion": true,
	"FFlagGraphicsGLEnableSuperHQShadersExclusion": true,
	"FFlagGraphicsVulkanDeviceLostCrash": true,
	"FFlagIsSendrNotificationSetupEnabled": true,
	"FFlagLuaAppAddFriendHintUsePolicy": true,
	"FFlagLuaAppAddFriendsTileUsePolicy": true,
	"FFlagLuaAppChallengeDisableForceWebViewVisible": true,
	"FFlagLuaAppEnablePasskeyLoginABTest": true,
	"FFlagLuaAppUseSettingsNativeWrapper2": true,
	"FFlagLuaAppVngUserAgreementEnabled": true,
	"FFlagLuaAppWaitBeforeTwoStepRenderDev": true,
	"FFlagLuaBridgeMethodProfiling": false,
	"FFlagLuaBridgePropertyProfiling": false,
	"FFlagLuaEnableDidSwitchAccount": true,
	"FFlagLuaIdentityGetPhoneNumber": true,
	"FFlagLuaIdentityGetSMSOTP": true,
	"FFlagLuaIdentityProtocol": true,
	"FFlagLuaUseIdentityProtocolForPhoneUpsell": true,
	"FFlagLuaVerifiedSignupExperiment2": true,
	"FFlagMinimalSignupAuthEnabled1": true,
	"FFlagMovePrerender_PlaceFilter": "False;7117492592",
	"FFlagNativePurchaseWithLocalPlayer": true,
	"FFlagNotchSupportExperimentTrackExposure": true,
	"FFlagOffNetworkFriendingEnabled_3": true,
	"FFlagOffPlatformFriendRequestsExperimentEnabled_v2": true,
	"FFlagPasskeySignupEnabled": true,
	"FFlagPhoneVerificationWebviewShouldBeFullscreen1": true,
	"FFlagRealtimeProtocolEnabledRolloutV2": true,
	"FFlagRenderEnableGlobalInstancingVulkan_PlaceFilter": "True;16303126094",
	"FFlagShouldHandleNotificationSettingChanged": true,
	"FFlagShouldUsePeekViewForLoginDisambiguation2": true,
	"FFlagShouldUseSelectionRowInAccountSelectionRelease1": true,
	"FFlagSimSolverOptimizeTimestepMultiplierChanges": true,
	"FFlagStartupDeprecationMessage": true,
	"FFlagStringStreamAllocsBegone": true,
	"FFlagStringStreamAllocsBegone2": true,
	"FFlagTeardownInSingleSurface": false,
	"FFlagTelemetryRevampClicks2": true,
	"FFlagTelemetryRevampPurchase3": true,
	"FFlagTrackDeeplinkLaunchFlow": true,
	"FFlagUpdateCheckOnLogin2": true,
	"FFlagUserSearchUseNewEndpointIXP": true,
	"FFlagVideoServiceAddHardwareCodecMetrics": true,
	"FFlagVideoVP9HardWareDecoderCap2": true,
	"FFlagVignetteEffectEnabled2": true,
	"FFlagVngContactInfoFormWebviewPopupEnabled": true,
	"FFlagVoiceUseUpdatedAudibilityTracking2": true,
	"FIntEnableContactInvitesForNonPhoneVerifiedRollout_v2": 100,
	"FIntFriendsCarouselUserProfileApiRollout": 100,
	"FIntLmsClientRollout2": 20,
	"FIntLuaAppGameDetailsMoreShareButtonRolloutV2": 100,
	"FIntLuaAppLoginMethod": 1,
	"FLogError_PlaceFilter": "0;3652625463",
	"FLogRenderInstanceGlob_PlaceFilter": "6;16303126094;5191483765",
	"FLogRenderTC2LogGroupContent": 0,
	"FLogRenderTC2LogGroupFlow": 0,
	"FLogScriptContextClose": 0,
	"FStringClientChannelProbabilityString": "1000;zflag=50",
	"FStringContactsToastButtonPressed": "ContactsToastButtonPressed_Android",
	"FStringContactsToastDismissed": "ContactsToastDismissed_Android",
	"FStringContactsToastSeen": "ContactsToastSeen_Android",
	"FStringFeature_SingleSurfaceEnabled": "581;0",
	"FStringFriendInviteVariantForSoothsayers": "blended",
	"FStringGraphicsGLGpuExcludeListHQShaders": "PowerVR.*;Vivante GC7000UL;Mali-T628;Mali-T624;Mali-T860;Adreno \\(TM\\) 304;Adreno \\(TM\\) 305;Adreno \\(TM\\) 306;Adreno \\(TM\\) 320;Adreno \\(TM\\) 330",
	"FStringGraphicsGLShlangExcludeListSuperHQShaders": "glsles3",
	"FStringLuaChatFetchedOlderConversationCounter": "LuaChatFetchedOlderConversationAndroid",
	"FStringRoactChatFetchedOlderConversationCounter": "RoactChatFetchedOlderConversationAndroid",
	"FStringShareLinkErrorDialogJoinButtonClick": "ShareLinkErrorDialogJoinButtonClickAndroid",
	"FStringSocialTabUserLoadedPageCounter": "SocialTabUserLoadedPageAndroid",
	"GrantPendingPurchaseInterval": 3600,
	"HandleSecureCookie": true,
	"InactivityDaysBeforeReminderNotification": 2,
	"InfluxThrottleRate": 10,
	"JavaANRUploadToBacktracePercentage": 1,
	"MaxNumberOfContactsToSync": 2000,
	"MinSupportedAPILevel": 21,
	"MinSupportedOSVersion": "5.0",
	"PercentReportingByCountryCode": 100,
	"RefactorExperienceSession": true,
	"SettingsValidIntervalInSecs": 864000,
	"SingleSurfaceEnabledAndroid3": true,
	"VisibleAgeStyleLuaApp": "More Only",
	"VisibleAgeStyleNativeShell": "More Only"
}