{
  "Type": "Platforms",
  "Value": {
    "AndroidApp": "false;SteadyState;10;15;Rollout;100;30;SteadyState;100;15;Promote;false;1079082761;2026-05-07T18:11:45",
    "iOSApp": "false;SteadyState;10;15;Rollout;100;30;SteadyState;100;15;Promote;false;1079082761;2026-05-07T18:11:45",
    "MacDesktopClient": "false;SteadyState;10;15;Rollout;100;30;SteadyState;100;15;Promote;false;1079082761;2026-05-07T18:11:45",
    "MacStudioApp": "false;SteadyState;10;15;Rollout;100;30;SteadyState;100;15;Promote;false;1079082761;2026-05-07T18:11:45",
    "PCDesktopClient": "false;SteadyState;10;15;Rollout;100;30;SteadyState;100;15;Promote;false;1079082761;2026-05-07T18:11:45",
    "PCStudioApp": "false;SteadyState;10;15;Rollout;100;30;SteadyState;100;15;Promote;false;1079082761;2026-05-07T18:11:45",
    "PlayStationClient": "false;SteadyState;10;15;Rollout;100;30;SteadyState;100;15;Promote;false;1079082761;2026-05-07T18:11:45",
    "XboxClient": "false;SteadyState;10;15;Rollout;100;30;SteadyState;100;15;Promote;false;1079082761;2026-05-07T18:11:45"
  }
}