{
  "Type": "ChannelsAndPlatforms",
  "Value": {
    "LIVE": {
      "AndroidApp": "08/25/2025 19:53:01",
      "iOSApp": "08/25/2025 19:44:08",
      "MacClientBootstrapper": "08/25/2025 19:44:08",
      "MacDesktopClient": "08/25/2025 19:44:08",
      "MacStudioApp": "08/25/2025 19:44:08",
      "MacStudioBootstrapper": "08/25/2025 19:53:01",
      "PCClientBootstrapper": "08/25/2025 19:44:08",
      "PCDesktopClient": "08/25/2025 19:44:08",
      "PCStudioApp": "08/25/2025 19:53:01",
      "PCStudioBootstrapper": "08/25/2025 19:44:08",
      "PlayStationClient": "08/25/2025 19:44:08",
      "UWPApp": "08/25/2025 19:44:08",
      "XboxClient": "08/25/2025 19:53:01"
    },
    "zcanary": {
      "AndroidApp": "08/25/2025 19:53:01",
      "iOSApp": "08/25/2025 19:44:08",
      "MacClientBootstrapper": "08/25/2025 19:44:08",
      "MacDesktopClient": "08/25/2025 19:44:08",
      "MacStudioApp": "08/25/2025 19:44:08",
      "MacStudioBootstrapper": "08/25/2025 19:53:01",
      "PCClientBootstrapper": "08/25/2025 19:44:08",
      "PCDesktopClient": "08/25/2025 19:44:08",
      "PCStudioApp": "08/25/2025 19:53:01",
      "PCStudioBootstrapper": "08/25/2025 19:53:01",
      "PlayStationClient": "08/25/2025 19:53:01",
      "UWPApp": "08/25/2025 19:53:01",
      "XboxClient": "08/25/2025 19:44:08"
    },
    "zintegration": {
      "AndroidApp": "08/25/2025 19:53:01",
      "iOSApp": "08/25/2025 19:53:01",
      "MacClientBootstrapper": "08/25/2025 19:44:08",
      "MacDesktopClient": "08/25/2025 19:53:01",
      "MacStudioApp": "08/25/2025 19:53:01",
      "MacStudioBootstrapper": "08/25/2025 19:53:01",
      "PCClientBootstrapper": "08/25/2025 19:44:08",
      "PCDesktopClient": "08/25/2025 19:44:08",
      "PCStudioApp": "08/25/2025 19:53:01",
      "PCStudioBootstrapper": "08/25/2025 19:53:01",
      "PlayStationClient": "08/25/2025 19:44:08",
      "UWPApp": "08/25/2025 19:53:01",
      "XboxClient": "08/25/2025 19:53:01"
    }
  }
}