{
  "Type": "ChannelsAndPlatforms",
  "Value": {
    "LIVE": {
      "AndroidApp": "06/17/2025 21:46:44",
      "iOSApp": "06/17/2025 21:46:44",
      "MacClientBootstrapper": "06/17/2025 21:46:44",
      "MacDesktopClient": "06/17/2025 21:46:44",
      "MacStudioApp": "06/17/2025 21:46:44",
      "MacStudioBootstrapper": "06/17/2025 21:46:44",
      "PCClientBootstrapper": "06/17/2025 21:47:09",
      "PCDesktopClient": "06/17/2025 21:46:44",
      "PCStudioApp": "06/17/2025 21:46:44",
      "PCStudioBootstrapper": "06/17/2025 21:46:44",
      "PlayStationClient": "06/17/2025 21:46:44",
      "UWPApp": "06/17/2025 21:46:44",
      "XboxClient": "06/17/2025 21:46:44"
    },
    "zcanary": {
      "AndroidApp": "06/17/2025 21:47:09",
      "iOSApp": "06/17/2025 21:46:44",
      "MacClientBootstrapper": "06/17/2025 21:47:09",
      "MacDesktopClient": "06/17/2025 21:47:09",
      "MacStudioApp": "06/17/2025 21:47:09",
      "MacStudioBootstrapper": "06/17/2025 21:46:44",
      "PCClientBootstrapper": "06/17/2025 21:47:09",
      "PCDesktopClient": "06/17/2025 21:46:44",
      "PCStudioApp": "06/17/2025 21:46:44",
      "PCStudioBootstrapper": "06/17/2025 21:47:09",
      "PlayStationClient": "06/17/2025 21:47:09",
      "UWPApp": "06/17/2025 21:47:09",
      "XboxClient": "06/17/2025 21:46:44"
    },
    "zintegration": {
      "AndroidApp": "06/17/2025 21:47:09",
      "iOSApp": "06/17/2025 21:47:09",
      "MacClientBootstrapper": "06/17/2025 21:47:09",
      "MacDesktopClient": "06/17/2025 21:47:09",
      "MacStudioApp": "06/17/2025 21:47:09",
      "MacStudioBootstrapper": "06/17/2025 21:47:09",
      "PCClientBootstrapper": "06/17/2025 21:47:09",
      "PCDesktopClient": "06/17/2025 21:46:44",
      "PCStudioApp": "06/17/2025 21:47:09",
      "PCStudioBootstrapper": "06/17/2025 21:47:09",
      "PlayStationClient": "06/17/2025 21:47:09",
      "UWPApp": "06/17/2025 21:47:09",
      "XboxClient": "06/17/2025 21:47:09"
    }
  }
}