{
  "Type": "ChannelsAndPlatforms",
  "Value": {
    "LIVE": {
      "AndroidApp": "01/20/2026 23:31:35",
      "iOSApp": "01/20/2026 23:32:42",
      "MacClientBootstrapper": "01/20/2026 23:31:35",
      "MacDesktopClient": "01/20/2026 23:31:35",
      "MacStudioApp": "01/20/2026 23:31:35",
      "MacStudioBootstrapper": "01/20/2026 23:32:42",
      "PCClientBootstrapper": "01/20/2026 23:31:35",
      "PCDesktopClient": "01/20/2026 23:31:35",
      "PCStudioApp": "01/20/2026 23:31:35",
      "PCStudioBootstrapper": "01/20/2026 23:31:35",
      "PlayStationClient": "01/20/2026 23:31:35",
      "UWPApp": "01/20/2026 23:31:35",
      "XboxClient": "01/20/2026 23:32:42"
    },
    "zcanary": {
      "AndroidApp": "01/20/2026 23:32:42",
      "iOSApp": "01/20/2026 23:32:42",
      "MacClientBootstrapper": "01/20/2026 23:32:42",
      "MacDesktopClient": "01/20/2026 23:32:42",
      "MacStudioApp": "01/20/2026 23:32:42",
      "MacStudioBootstrapper": "01/20/2026 23:32:42",
      "PCClientBootstrapper": "01/20/2026 23:32:42",
      "PCDesktopClient": "01/20/2026 23:32:42",
      "PCStudioApp": "01/20/2026 23:32:42",
      "PCStudioBootstrapper": "01/20/2026 23:32:42",
      "PlayStationClient": "01/20/2026 23:32:42",
      "UWPApp": "01/20/2026 23:32:42",
      "XboxClient": "01/20/2026 23:32:42"
    },
    "zintegration": {
      "AndroidApp": "01/20/2026 23:32:42",
      "iOSApp": "01/20/2026 23:32:42",
      "MacClientBootstrapper": "01/20/2026 23:32:42",
      "MacDesktopClient": "01/20/2026 23:32:42",
      "MacStudioApp": "01/20/2026 23:32:42",
      "MacStudioBootstrapper": "01/20/2026 23:32:42",
      "PCClientBootstrapper": "01/20/2026 23:32:42",
      "PCDesktopClient": "01/20/2026 23:32:42",
      "PCStudioApp": "01/20/2026 23:32:42",
      "PCStudioBootstrapper": "01/20/2026 23:32:42",
      "PlayStationClient": "01/20/2026 23:32:42",
      "UWPApp": "01/20/2026 23:32:42",
      "XboxClient": "01/20/2026 23:32:42"
    }
  }
}