{
  "Type": "ChannelsAndPlatforms",
  "Value": {
    "LIVE": {
      "AndroidApp": "05/12/2025 16:20:22",
      "iOSApp": "05/12/2025 16:20:22",
      "MacClientBootstrapper": "05/12/2025 16:20:22",
      "MacDesktopClient": "05/12/2025 16:20:22",
      "MacStudioApp": "05/12/2025 16:20:22",
      "MacStudioBootstrapper": "05/12/2025 16:20:22",
      "PCClientBootstrapper": "05/12/2025 16:17:54",
      "PCDesktopClient": "05/12/2025 16:20:22",
      "PCStudioApp": "05/12/2025 16:20:22",
      "PCStudioBootstrapper": "05/12/2025 16:20:22",
      "PlayStationClient": "05/12/2025 16:20:22",
      "UWPApp": "05/12/2025 16:20:22",
      "XboxClient": "05/12/2025 16:20:22"
    },
    "zcanary": {
      "AndroidApp": "05/12/2025 16:20:22",
      "iOSApp": "05/12/2025 16:20:22",
      "MacClientBootstrapper": "05/12/2025 16:20:22",
      "MacDesktopClient": "05/12/2025 16:20:22",
      "MacStudioApp": "05/12/2025 16:20:22",
      "MacStudioBootstrapper": "05/12/2025 16:20:22",
      "PCClientBootstrapper": "05/12/2025 16:20:22",
      "PCDesktopClient": "05/12/2025 16:20:22",
      "PCStudioApp": "05/12/2025 16:20:22",
      "PCStudioBootstrapper": "05/12/2025 16:20:22",
      "PlayStationClient": "05/12/2025 16:20:22",
      "UWPApp": "05/12/2025 16:20:22",
      "XboxClient": "05/12/2025 16:20:22"
    },
    "zintegration": {
      "AndroidApp": "05/12/2025 16:20:22",
      "iOSApp": "05/12/2025 16:20:22",
      "MacClientBootstrapper": "05/12/2025 16:20:22",
      "MacDesktopClient": "05/12/2025 16:20:22",
      "MacStudioApp": "05/12/2025 16:20:22",
      "MacStudioBootstrapper": "05/12/2025 16:20:22",
      "PCClientBootstrapper": "05/12/2025 16:20:22",
      "PCDesktopClient": "05/12/2025 16:20:22",
      "PCStudioApp": "05/12/2025 16:20:22",
      "PCStudioBootstrapper": "05/12/2025 16:20:22",
      "PlayStationClient": "05/12/2025 16:20:22",
      "UWPApp": "05/12/2025 16:20:22",
      "XboxClient": "05/12/2025 16:20:22"
    }
  }
}