{
  "Type": "ChannelsAndPlatforms",
  "Value": {
    "LIVE": {
      "AndroidApp": "07/23/2026 23:42:59",
      "iOSApp": "07/23/2026 23:42:59",
      "MacClientBootstrapper": "07/23/2026 23:42:59",
      "MacDesktopClient": "07/23/2026 23:42:59",
      "MacStudioApp": "07/23/2026 23:42:59",
      "MacStudioBootstrapper": "07/23/2026 23:42:59",
      "PCClientBootstrapper": "07/23/2026 23:42:59",
      "PCDesktopClient": "07/23/2026 23:42:59",
      "PCStudioApp": "07/23/2026 23:42:59",
      "PCStudioBootstrapper": "07/23/2026 23:42:59",
      "PlayStationClient": "07/23/2026 23:42:59",
      "UWPApp": "07/23/2026 23:42:59",
      "XboxClient": "07/23/2026 23:42:59"
    },
    "zcanary": {
      "AndroidApp": "07/23/2026 23:42:59",
      "iOSApp": "07/23/2026 23:42:59",
      "MacClientBootstrapper": "07/23/2026 23:42:59",
      "MacDesktopClient": "07/23/2026 23:42:59",
      "MacStudioApp": "07/23/2026 23:42:59",
      "MacStudioBootstrapper": "07/23/2026 23:42:59",
      "PCClientBootstrapper": "07/23/2026 23:42:59",
      "PCDesktopClient": "07/23/2026 23:42:59",
      "PCStudioApp": "07/23/2026 23:42:59",
      "PCStudioBootstrapper": "07/23/2026 23:42:59",
      "PlayStationClient": "07/23/2026 23:42:59",
      "UWPApp": "07/23/2026 23:42:59",
      "XboxClient": "07/23/2026 23:42:59"
    },
    "zintegration": {
      "AndroidApp": "07/23/2026 23:42:59",
      "iOSApp": "07/23/2026 23:42:59",
      "MacClientBootstrapper": "07/23/2026 23:42:59",
      "MacDesktopClient": "07/23/2026 23:42:59",
      "MacStudioApp": "07/23/2026 23:42:59",
      "MacStudioBootstrapper": "07/23/2026 23:52:40",
      "PCClientBootstrapper": "07/23/2026 23:42:59",
      "PCDesktopClient": "07/23/2026 23:42:59",
      "PCStudioApp": "07/23/2026 23:42:59",
      "PCStudioBootstrapper": "07/23/2026 23:42:59",
      "PlayStationClient": "07/23/2026 23:42:59",
      "UWPApp": "07/23/2026 23:42:59",
      "XboxClient": "07/23/2026 23:42:59"
    }
  }
}