{
  "Type": "ChannelsAndPlatforms",
  "Value": {
    "LIVE": {
      "AndroidApp": "09/24/2024 21:27:41",
      "iOSApp": "09/24/2024 21:27:41",
      "MacClientBootstrapper": "09/24/2024 21:27:41",
      "MacDesktopClient": "09/24/2024 21:27:41",
      "MacStudioApp": "09/24/2024 21:27:41",
      "MacStudioBootstrapper": "09/24/2024 21:27:41",
      "PCClientBootstrapper": "09/24/2024 21:27:41",
      "PCDesktopClient": "09/24/2024 21:27:41",
      "PCStudioApp": "09/24/2024 21:27:41",
      "PCStudioBootstrapper": "09/24/2024 21:14:11",
      "PlayStationClient": "09/24/2024 21:27:41",
      "UWPApp": "09/24/2024 21:27:41",
      "XboxClient": "09/24/2024 21:27:41"
    },
    "zcanary": {
      "AndroidApp": "09/24/2024 21:27:41",
      "iOSApp": "09/24/2024 21:27:41",
      "MacClientBootstrapper": "09/24/2024 21:27:41",
      "MacDesktopClient": "09/24/2024 21:27:41",
      "MacStudioApp": "09/24/2024 21:27:41",
      "MacStudioBootstrapper": "09/24/2024 21:27:41",
      "PCClientBootstrapper": "09/24/2024 21:27:41",
      "PCDesktopClient": "09/24/2024 21:27:41",
      "PCStudioApp": "09/24/2024 21:27:41",
      "PCStudioBootstrapper": "09/24/2024 21:27:41",
      "PlayStationClient": "09/24/2024 21:27:41",
      "UWPApp": "09/24/2024 21:27:41",
      "XboxClient": "09/24/2024 21:27:41"
    },
    "zintegration": {
      "AndroidApp": "09/24/2024 21:27:41",
      "iOSApp": "09/24/2024 21:27:41",
      "MacClientBootstrapper": "09/24/2024 21:27:41",
      "MacDesktopClient": "09/24/2024 21:27:41",
      "MacStudioApp": "09/24/2024 21:27:41",
      "MacStudioBootstrapper": "09/24/2024 21:27:41",
      "PCClientBootstrapper": "09/24/2024 21:27:41",
      "PCDesktopClient": "09/24/2024 21:27:41",
      "PCStudioApp": "09/24/2024 21:27:41",
      "PCStudioBootstrapper": "09/24/2024 21:27:41",
      "PlayStationClient": "09/24/2024 21:27:41",
      "UWPApp": "09/24/2024 21:27:41",
      "XboxClient": "09/24/2024 21:27:41"
    }
  }
}