{
  "Type": "ChannelsAndPlatforms",
  "Value": {
    "LIVE": {
      "AndroidApp": "11/07/2025 17:54:01",
      "iOSApp": "11/07/2025 18:02:09",
      "MacClientBootstrapper": "11/07/2025 17:54:01",
      "MacDesktopClient": "11/07/2025 18:02:09",
      "MacStudioApp": "11/07/2025 17:54:01",
      "MacStudioBootstrapper": "11/07/2025 18:02:09",
      "PCClientBootstrapper": "11/07/2025 18:02:09",
      "PCDesktopClient": "11/07/2025 17:54:01",
      "PCStudioApp": "11/07/2025 18:02:09",
      "PCStudioBootstrapper": "11/07/2025 18:02:09",
      "PlayStationClient": "11/07/2025 18:02:09",
      "UWPApp": "11/07/2025 17:54:01",
      "XboxClient": "11/07/2025 18:02:09"
    },
    "zcanary": {
      "AndroidApp": "11/07/2025 18:02:09",
      "iOSApp": "11/07/2025 18:02:09",
      "MacClientBootstrapper": "11/07/2025 18:02:09",
      "MacDesktopClient": "11/07/2025 18:02:09",
      "MacStudioApp": "11/07/2025 18:02:09",
      "MacStudioBootstrapper": "11/07/2025 18:02:09",
      "PCClientBootstrapper": "11/07/2025 18:02:09",
      "PCDesktopClient": "11/07/2025 18:02:09",
      "PCStudioApp": "11/07/2025 18:02:09",
      "PCStudioBootstrapper": "11/07/2025 18:02:09",
      "PlayStationClient": "11/07/2025 18:02:09",
      "UWPApp": "11/07/2025 18:02:09",
      "XboxClient": "11/07/2025 18:02:09"
    },
    "zintegration": {
      "AndroidApp": "11/07/2025 18:02:09",
      "iOSApp": "11/07/2025 18:02:09",
      "MacClientBootstrapper": "11/07/2025 18:02:09",
      "MacDesktopClient": "11/07/2025 18:02:09",
      "MacStudioApp": "11/07/2025 18:02:09",
      "MacStudioBootstrapper": "11/07/2025 18:02:09",
      "PCClientBootstrapper": "11/07/2025 18:02:09",
      "PCDesktopClient": "11/07/2025 18:02:09",
      "PCStudioApp": "11/07/2025 18:02:09",
      "PCStudioBootstrapper": "11/07/2025 18:02:09",
      "PlayStationClient": "11/07/2025 18:02:09",
      "UWPApp": "11/07/2025 18:02:09",
      "XboxClient": "11/07/2025 18:02:09"
    }
  }
}