{
  "Type": "ChannelsAndPlatforms",
  "Value": {
    "LIVE": {
      "AndroidApp": "05/19/2025 22:27:31",
      "iOSApp": "05/19/2025 22:37:18",
      "MacClientBootstrapper": "05/19/2025 22:37:18",
      "MacDesktopClient": "05/19/2025 22:37:18",
      "MacStudioApp": "05/19/2025 22:37:18",
      "MacStudioBootstrapper": "05/19/2025 22:37:18",
      "PCClientBootstrapper": "05/19/2025 22:27:31",
      "PCDesktopClient": "05/19/2025 22:37:18",
      "PCStudioApp": "05/19/2025 22:37:18",
      "PCStudioBootstrapper": "05/19/2025 22:37:18",
      "PlayStationClient": "05/19/2025 22:37:18",
      "UWPApp": "05/19/2025 22:27:31",
      "XboxClient": "05/19/2025 22:27:31"
    },
    "zcanary": {
      "AndroidApp": "05/19/2025 22:37:18",
      "iOSApp": "05/19/2025 22:37:18",
      "MacClientBootstrapper": "05/19/2025 22:37:18",
      "MacDesktopClient": "05/19/2025 22:37:18",
      "MacStudioApp": "05/19/2025 22:37:18",
      "MacStudioBootstrapper": "05/19/2025 22:37:18",
      "PCClientBootstrapper": "05/19/2025 22:37:18",
      "PCDesktopClient": "05/19/2025 22:37:18",
      "PCStudioApp": "05/19/2025 22:37:18",
      "PCStudioBootstrapper": "05/19/2025 22:37:18",
      "PlayStationClient": "05/19/2025 22:37:18",
      "UWPApp": "05/19/2025 22:37:18",
      "XboxClient": "05/19/2025 22:37:18"
    },
    "zintegration": {
      "AndroidApp": "05/19/2025 22:37:18",
      "iOSApp": "05/19/2025 22:37:18",
      "MacClientBootstrapper": "05/19/2025 22:37:18",
      "MacDesktopClient": "05/19/2025 22:37:18",
      "MacStudioApp": "05/19/2025 22:37:18",
      "MacStudioBootstrapper": "05/19/2025 22:37:18",
      "PCClientBootstrapper": "05/19/2025 22:37:18",
      "PCDesktopClient": "05/19/2025 22:37:18",
      "PCStudioApp": "05/19/2025 22:37:18",
      "PCStudioBootstrapper": "05/19/2025 22:37:18",
      "PlayStationClient": "05/19/2025 22:37:18",
      "UWPApp": "05/19/2025 22:37:18",
      "XboxClient": "05/19/2025 22:37:18"
    }
  }
}