{
  "Type": "ChannelsAndPlatforms",
  "Value": {
    "LIVE": {
      "AndroidApp": "10/06/2025 22:06:57",
      "iOSApp": "10/06/2025 22:06:57",
      "MacClientBootstrapper": "10/06/2025 22:06:57",
      "MacDesktopClient": "10/06/2025 22:06:57",
      "MacStudioApp": "10/06/2025 22:06:57",
      "MacStudioBootstrapper": "10/06/2025 22:06:57",
      "PCClientBootstrapper": "10/06/2025 22:06:57",
      "PCDesktopClient": "10/06/2025 22:06:57",
      "PCStudioApp": "10/06/2025 22:06:57",
      "PCStudioBootstrapper": "10/06/2025 22:06:57",
      "PlayStationClient": "10/06/2025 22:06:57",
      "UWPApp": "10/06/2025 22:03:14",
      "XboxClient": "10/06/2025 22:06:57"
    },
    "zcanary": {
      "AndroidApp": "10/06/2025 22:06:57",
      "iOSApp": "10/06/2025 22:06:57",
      "MacClientBootstrapper": "10/06/2025 22:06:57",
      "MacDesktopClient": "10/06/2025 22:06:57",
      "MacStudioApp": "10/06/2025 22:06:57",
      "MacStudioBootstrapper": "10/06/2025 22:06:57",
      "PCClientBootstrapper": "10/06/2025 22:06:57",
      "PCDesktopClient": "10/06/2025 22:06:57",
      "PCStudioApp": "10/06/2025 22:06:57",
      "PCStudioBootstrapper": "10/06/2025 22:06:57",
      "PlayStationClient": "10/06/2025 22:06:57",
      "UWPApp": "10/06/2025 22:06:57",
      "XboxClient": "10/06/2025 22:06:57"
    },
    "zintegration": {
      "AndroidApp": "10/06/2025 22:06:57",
      "iOSApp": "10/06/2025 22:06:57",
      "MacClientBootstrapper": "10/06/2025 22:06:57",
      "MacDesktopClient": "10/06/2025 22:06:57",
      "MacStudioApp": "10/06/2025 22:06:57",
      "MacStudioBootstrapper": "10/06/2025 22:06:57",
      "PCClientBootstrapper": "10/06/2025 22:06:57",
      "PCDesktopClient": "10/06/2025 22:06:57",
      "PCStudioApp": "10/06/2025 22:06:57",
      "PCStudioBootstrapper": "10/06/2025 22:06:57",
      "PlayStationClient": "10/06/2025 22:06:57",
      "UWPApp": "10/06/2025 22:06:57",
      "XboxClient": "10/06/2025 22:06:57"
    }
  }
}