{
  "Type": "ChannelsAndPlatforms",
  "Value": {
    "LIVE": {
      "AndroidApp": "01/07/2025 21:02:28",
      "iOSApp": "01/07/2025 21:02:28",
      "MacClientBootstrapper": "01/07/2025 21:02:28",
      "MacDesktopClient": "01/07/2025 21:02:28",
      "MacStudioApp": "01/07/2025 21:02:28",
      "MacStudioBootstrapper": "01/07/2025 21:02:28",
      "PCClientBootstrapper": "01/07/2025 21:02:28",
      "PCDesktopClient": "01/07/2025 21:02:28",
      "PCStudioApp": "01/07/2025 21:02:28",
      "PCStudioBootstrapper": "01/07/2025 21:02:28",
      "PlayStationClient": "01/07/2025 21:02:28",
      "UWPApp": "01/07/2025 21:02:28",
      "XboxClient": "01/07/2025 21:02:28"
    },
    "zcanary": {
      "AndroidApp": "01/07/2025 21:02:28",
      "iOSApp": "01/07/2025 21:02:28",
      "MacClientBootstrapper": "01/07/2025 21:02:28",
      "MacDesktopClient": "01/07/2025 21:02:28",
      "MacStudioApp": "01/07/2025 21:02:28",
      "MacStudioBootstrapper": "01/07/2025 21:02:28",
      "PCClientBootstrapper": "01/07/2025 21:02:28",
      "PCDesktopClient": "01/07/2025 21:02:28",
      "PCStudioApp": "01/07/2025 21:02:28",
      "PCStudioBootstrapper": "01/07/2025 21:02:28",
      "PlayStationClient": "01/07/2025 21:02:28",
      "UWPApp": "01/07/2025 21:02:28",
      "XboxClient": "01/07/2025 21:02:28"
    },
    "zintegration": {
      "AndroidApp": "01/07/2025 21:02:28",
      "iOSApp": "01/07/2025 21:02:28",
      "MacClientBootstrapper": "01/07/2025 21:02:28",
      "MacDesktopClient": "01/07/2025 21:02:28",
      "MacStudioApp": "01/07/2025 21:02:28",
      "MacStudioBootstrapper": "01/07/2025 21:02:28",
      "PCClientBootstrapper": "01/07/2025 21:02:28",
      "PCDesktopClient": "01/07/2025 21:02:28",
      "PCStudioApp": "01/07/2025 21:02:28",
      "PCStudioBootstrapper": "01/07/2025 21:02:28",
      "PlayStationClient": "01/07/2025 21:02:28",
      "UWPApp": "01/07/2025 21:02:28",
      "XboxClient": "01/07/2025 20:56:46"
    }
  }
}