{
  "Type": "ChannelsAndPlatforms",
  "Value": {
    "LIVE": {
      "AndroidApp": "04/30/2026 18:38:50",
      "iOSApp": "04/30/2026 18:38:50",
      "MacClientBootstrapper": "04/30/2026 18:38:50",
      "MacDesktopClient": "04/30/2026 18:38:50",
      "MacStudioApp": "04/30/2026 18:38:50",
      "MacStudioBootstrapper": "04/30/2026 18:38:50",
      "PCClientBootstrapper": "04/30/2026 18:38:50",
      "PCDesktopClient": "04/30/2026 18:38:50",
      "PCStudioApp": "04/30/2026 18:38:50",
      "PCStudioBootstrapper": "04/30/2026 18:38:50",
      "PlayStationClient": "04/30/2026 18:38:50",
      "UWPApp": "04/30/2026 18:38:50",
      "XboxClient": "04/30/2026 18:38:50"
    },
    "zcanary": {
      "AndroidApp": "04/30/2026 18:40:59",
      "iOSApp": "04/30/2026 18:40:59",
      "MacClientBootstrapper": "04/30/2026 18:40:59",
      "MacDesktopClient": "04/30/2026 18:38:50",
      "MacStudioApp": "04/30/2026 18:38:50",
      "MacStudioBootstrapper": "04/30/2026 18:40:59",
      "PCClientBootstrapper": "04/30/2026 18:38:50",
      "PCDesktopClient": "04/30/2026 18:38:50",
      "PCStudioApp": "04/30/2026 18:38:50",
      "PCStudioBootstrapper": "04/30/2026 18:38:50",
      "PlayStationClient": "04/30/2026 18:40:59",
      "UWPApp": "04/30/2026 18:38:50",
      "XboxClient": "04/30/2026 18:38:50"
    },
    "zintegration": {
      "AndroidApp": "04/30/2026 18:40:59",
      "iOSApp": "04/30/2026 18:38:50",
      "MacClientBootstrapper": "04/30/2026 18:38:50",
      "MacDesktopClient": "04/30/2026 18:40:59",
      "MacStudioApp": "04/30/2026 18:40:59",
      "MacStudioBootstrapper": "04/30/2026 18:40:59",
      "PCClientBootstrapper": "04/30/2026 18:40:59",
      "PCDesktopClient": "04/30/2026 18:40:59",
      "PCStudioApp": "04/30/2026 18:40:59",
      "PCStudioBootstrapper": "04/30/2026 18:40:59",
      "PlayStationClient": "04/30/2026 18:38:50",
      "UWPApp": "04/30/2026 18:40:59",
      "XboxClient": "04/30/2026 18:40:59"
    }
  }
}