{
  "Type": "ChannelsAndPlatforms",
  "Value": {
    "LIVE": {
      "AndroidApp": "12/11/2025 23:56:40",
      "iOSApp": "12/11/2025 23:56:40",
      "MacClientBootstrapper": "12/11/2025 23:56:40",
      "MacDesktopClient": "12/11/2025 23:56:40",
      "MacStudioApp": "12/11/2025 23:56:40",
      "MacStudioBootstrapper": "12/11/2025 23:56:40",
      "PCClientBootstrapper": "12/11/2025 23:56:40",
      "PCDesktopClient": "12/11/2025 23:56:40",
      "PCStudioApp": "12/11/2025 23:56:40",
      "PCStudioBootstrapper": "12/11/2025 23:56:40",
      "PlayStationClient": "12/11/2025 23:56:40",
      "UWPApp": "12/11/2025 23:55:37",
      "XboxClient": "12/11/2025 23:56:40"
    },
    "zcanary": {
      "AndroidApp": "12/11/2025 23:56:40",
      "iOSApp": "12/11/2025 23:56:40",
      "MacClientBootstrapper": "12/11/2025 23:56:40",
      "MacDesktopClient": "12/11/2025 23:56:40",
      "MacStudioApp": "12/11/2025 23:56:40",
      "MacStudioBootstrapper": "12/11/2025 23:56:40",
      "PCClientBootstrapper": "12/11/2025 23:56:40",
      "PCDesktopClient": "12/11/2025 23:56:40",
      "PCStudioApp": "12/11/2025 23:56:40",
      "PCStudioBootstrapper": "12/11/2025 23:56:40",
      "PlayStationClient": "12/11/2025 23:56:40",
      "UWPApp": "12/11/2025 23:56:40",
      "XboxClient": "12/11/2025 23:56:40"
    },
    "zintegration": {
      "AndroidApp": "12/11/2025 23:56:40",
      "iOSApp": "12/11/2025 23:56:40",
      "MacClientBootstrapper": "12/11/2025 23:56:40",
      "MacDesktopClient": "12/11/2025 23:56:40",
      "MacStudioApp": "12/11/2025 23:56:40",
      "MacStudioBootstrapper": "12/11/2025 23:56:40",
      "PCClientBootstrapper": "12/11/2025 23:56:40",
      "PCDesktopClient": "12/11/2025 23:56:40",
      "PCStudioApp": "12/11/2025 23:56:40",
      "PCStudioBootstrapper": "12/11/2025 23:56:40",
      "PlayStationClient": "12/11/2025 23:56:40",
      "UWPApp": "12/11/2025 23:56:40",
      "XboxClient": "12/11/2025 23:56:40"
    }
  }
}