{
  "Type": "ChannelsAndPlatforms",
  "Value": {
    "LIVE": {
      "AndroidApp": "05/13/2026 21:24:02",
      "iOSApp": "05/13/2026 21:24:02",
      "MacClientBootstrapper": "05/13/2026 21:24:02",
      "MacDesktopClient": "05/13/2026 21:24:02",
      "MacStudioApp": "05/13/2026 21:24:02",
      "MacStudioBootstrapper": "05/13/2026 21:24:02",
      "PCClientBootstrapper": "05/13/2026 21:24:02",
      "PCDesktopClient": "05/13/2026 21:24:02",
      "PCStudioApp": "05/13/2026 21:24:02",
      "PCStudioBootstrapper": "05/13/2026 21:24:02",
      "PlayStationClient": "05/13/2026 21:24:02",
      "UWPApp": "05/13/2026 21:24:02",
      "XboxClient": "05/13/2026 21:24:02"
    },
    "zcanary": {
      "AndroidApp": "05/13/2026 21:24:02",
      "iOSApp": "05/13/2026 21:24:02",
      "MacClientBootstrapper": "05/13/2026 21:24:02",
      "MacDesktopClient": "05/13/2026 21:24:02",
      "MacStudioApp": "05/13/2026 21:24:02",
      "MacStudioBootstrapper": "05/13/2026 21:24:02",
      "PCClientBootstrapper": "05/13/2026 21:24:02",
      "PCDesktopClient": "05/13/2026 21:24:02",
      "PCStudioApp": "05/13/2026 21:24:02",
      "PCStudioBootstrapper": "05/13/2026 21:24:02",
      "PlayStationClient": "05/13/2026 21:24:02",
      "UWPApp": "05/13/2026 21:24:02",
      "XboxClient": "05/13/2026 21:24:02"
    },
    "zintegration": {
      "AndroidApp": "05/13/2026 21:24:02",
      "iOSApp": "05/13/2026 21:24:02",
      "MacClientBootstrapper": "05/13/2026 21:25:27",
      "MacDesktopClient": "05/13/2026 21:24:02",
      "MacStudioApp": "05/13/2026 21:24:02",
      "MacStudioBootstrapper": "05/13/2026 21:25:27",
      "PCClientBootstrapper": "05/13/2026 21:25:27",
      "PCDesktopClient": "05/13/2026 21:24:02",
      "PCStudioApp": "05/13/2026 21:25:27",
      "PCStudioBootstrapper": "05/13/2026 21:25:27",
      "PlayStationClient": "05/13/2026 21:25:27",
      "UWPApp": "05/13/2026 21:25:27",
      "XboxClient": "05/13/2026 21:24:02"
    }
  }
}