{
  "Type": "ChannelsAndPlatforms",
  "Value": {
    "LIVE": {
      "AndroidApp": "09/17/2025 22:06:38",
      "iOSApp": "09/17/2025 22:06:38",
      "MacClientBootstrapper": "09/17/2025 22:06:38",
      "MacDesktopClient": "09/17/2025 22:06:38",
      "MacStudioApp": "09/17/2025 22:06:38",
      "MacStudioBootstrapper": "09/17/2025 22:06:38",
      "PCClientBootstrapper": "09/17/2025 22:06:38",
      "PCDesktopClient": "09/17/2025 22:06:38",
      "PCStudioApp": "09/17/2025 22:06:38",
      "PCStudioBootstrapper": "09/17/2025 22:06:38",
      "PlayStationClient": "09/17/2025 22:06:38",
      "UWPApp": "09/17/2025 22:06:38",
      "XboxClient": "09/17/2025 22:06:38"
    },
    "zcanary": {
      "AndroidApp": "09/17/2025 22:12:40",
      "iOSApp": "09/17/2025 22:06:38",
      "MacClientBootstrapper": "09/17/2025 22:12:40",
      "MacDesktopClient": "09/17/2025 22:06:38",
      "MacStudioApp": "09/17/2025 22:12:40",
      "MacStudioBootstrapper": "09/17/2025 22:06:38",
      "PCClientBootstrapper": "09/17/2025 22:12:40",
      "PCDesktopClient": "09/17/2025 22:06:38",
      "PCStudioApp": "09/17/2025 22:06:38",
      "PCStudioBootstrapper": "09/17/2025 22:06:38",
      "PlayStationClient": "09/17/2025 22:06:38",
      "UWPApp": "09/17/2025 22:06:38",
      "XboxClient": "09/17/2025 22:06:38"
    },
    "zintegration": {
      "AndroidApp": "09/17/2025 22:12:40",
      "iOSApp": "09/17/2025 22:12:40",
      "MacClientBootstrapper": "09/17/2025 22:12:40",
      "MacDesktopClient": "09/17/2025 22:06:38",
      "MacStudioApp": "09/17/2025 22:06:38",
      "MacStudioBootstrapper": "09/17/2025 22:12:40",
      "PCClientBootstrapper": "09/17/2025 22:12:40",
      "PCDesktopClient": "09/17/2025 22:06:38",
      "PCStudioApp": "09/17/2025 22:12:40",
      "PCStudioBootstrapper": "09/17/2025 22:06:38",
      "PlayStationClient": "09/17/2025 22:06:38",
      "UWPApp": "09/17/2025 22:06:38",
      "XboxClient": "09/17/2025 22:06:38"
    }
  }
}