{
  "Type": "ChannelsAndPlatforms",
  "Value": {
    "LIVE": {
      "AndroidApp": "04/17/2026 17:33:41",
      "iOSApp": "04/17/2026 17:33:41",
      "MacClientBootstrapper": "04/17/2026 17:28:59",
      "MacDesktopClient": "04/17/2026 17:33:41",
      "MacStudioApp": "04/17/2026 17:33:41",
      "MacStudioBootstrapper": "04/17/2026 17:33:41",
      "PCClientBootstrapper": "04/17/2026 17:28:59",
      "PCDesktopClient": "04/17/2026 17:33:41",
      "PCStudioApp": "04/17/2026 17:33:41",
      "PCStudioBootstrapper": "04/17/2026 17:28:59",
      "PlayStationClient": "04/17/2026 17:28:59",
      "UWPApp": "04/17/2026 17:28:59",
      "XboxClient": "04/17/2026 17:28:59"
    },
    "zcanary": {
      "AndroidApp": "04/17/2026 17:33:41",
      "iOSApp": "04/17/2026 17:33:41",
      "MacClientBootstrapper": "04/17/2026 17:33:41",
      "MacDesktopClient": "04/17/2026 17:33:41",
      "MacStudioApp": "04/17/2026 17:33:41",
      "MacStudioBootstrapper": "04/17/2026 17:33:41",
      "PCClientBootstrapper": "04/17/2026 17:33:41",
      "PCDesktopClient": "04/17/2026 17:33:41",
      "PCStudioApp": "04/17/2026 17:33:41",
      "PCStudioBootstrapper": "04/17/2026 17:33:41",
      "PlayStationClient": "04/17/2026 17:33:41",
      "UWPApp": "04/17/2026 17:33:41",
      "XboxClient": "04/17/2026 17:33:41"
    },
    "zintegration": {
      "AndroidApp": "04/17/2026 17:33:41",
      "iOSApp": "04/17/2026 17:33:41",
      "MacClientBootstrapper": "04/17/2026 17:33:41",
      "MacDesktopClient": "04/17/2026 17:33:41",
      "MacStudioApp": "04/17/2026 17:33:41",
      "MacStudioBootstrapper": "04/17/2026 17:33:41",
      "PCClientBootstrapper": "04/17/2026 17:33:41",
      "PCDesktopClient": "04/17/2026 17:33:41",
      "PCStudioApp": "04/17/2026 17:33:41",
      "PCStudioBootstrapper": "04/17/2026 17:33:41",
      "PlayStationClient": "04/17/2026 17:33:41",
      "UWPApp": "04/17/2026 17:33:41",
      "XboxClient": "04/17/2026 17:33:41"
    }
  }
}